{
  "pair_id": "mx-coa_manufactura_total__us-tx_manufactura_total",
  "sector": {
    "id": "manufactura_total",
    "scian": "31-33",
    "naics": "31-33",
    "label": "Manufactura total (referencia nacional)"
  },
  "series_a": {
    "id": "mx-coa_manufactura_total_itaee",
    "source": "INEGI - ITAEE (mock)",
    "region": "05",
    "proxy_type": "output_index",
    "seasonal_adjustment": "nsa"
  },
  "series_b": {
    "id": "us-tx_manufactura_total_coa_bls",
    "source": "BLS - State and Area Employment (mock)",
    "region": "48",
    "proxy_type": "labor_input",
    "seasonal_adjustment": "nsa"
  },
  "sample": {
    "frequency_used": "quarterly",
    "start": "2010-03-31",
    "end": "2026-06-30",
    "n_obs": 66
  },
  "generated_at": "2026-07-17T21:21:32.473115+00:00",
  "data_vintage": "2026-10-03",
  "data_vintage_detail": {
    "a": "2026-10-03",
    "b": "2026-07-21"
  },
  "insufficient_data": false,
  "stationarity": {
    "a": {
      "adf_statistic": -7.624549940809673,
      "adf_p_value": 2.0853868824785654e-11,
      "kpss_statistic": 0.14350405976883546,
      "kpss_p_value": 0.1,
      "is_stationary": true,
      "order_of_integration": 1,
      "log_transformed": true
    },
    "b": {
      "adf_statistic": -8.713311071605418,
      "adf_p_value": 3.5428481730266945e-14,
      "kpss_statistic": 0.18679615363418325,
      "kpss_p_value": 0.1,
      "is_stationary": true,
      "order_of_integration": 1,
      "log_transformed": true
    }
  },
  "granger": {
    "optimal_lag": 1,
    "selection_criterion": "bic",
    "a_causes_b": {
      "f_stat": 3.254879481255248,
      "p_value": 0.07367841184432214,
      "p_value_fdr_adj": 0.18484979178808286,
      "significant": false
    },
    "b_causes_a": {
      "f_stat": 2.2973382098871196,
      "p_value": 0.13218265396371295,
      "p_value_fdr_adj": 0.26460476792167953,
      "significant": false
    }
  },
  "cointegration_engle_granger": {
    "statistic": -5.761433137020478,
    "p_value": 5.214778696978719e-06,
    "cointegrated": true
  },
  "cointegration_johansen": {
    "trace_statistic": [
      28.906775052898645,
      0.5271310802160952
    ],
    "critical_values": [
      [
        13.4294,
        15.4943,
        19.9349
      ],
      [
        2.7055,
        3.8415,
        6.6349
      ]
    ],
    "cointegration_rank": 1
  },
  "vecm": {
    "cointegration_vector": [
      1.0,
      -1.3909016852888327
    ],
    "adjustment_speed": [
      -0.2004854988774034,
      0.5124671848813548
    ]
  },
  "warnings": []
}