{
  "id": "mx-tam_aeroespacial_itaee",
  "meta": {
    "id": "mx-tam_aeroespacial_itaee",
    "nombre": "ITAEE - Actividad industrial (Tamaulipas)",
    "pais": "MX",
    "region_code": "28",
    "sector_id": "aeroespacial",
    "fuente": "INEGI - ITAEE (mock)",
    "periodicidad": "trimestral",
    "unidad": "Índice base 2018=100 (sintético)",
    "proxy_type": "output_index",
    "ultima_actualizacion": "2026-06-30",
    "proxima_actualizacion_estimada": "2026-09-30"
  },
  "observations": [
    {
      "period": "2010-Q1",
      "value": 101.31875032624372
    },
    {
      "period": "2010-Q2",
      "value": 103.39999683241923
    },
    {
      "period": "2010-Q3",
      "value": 102.83415772908984
    },
    {
      "period": "2010-Q4",
      "value": 102.82468858780229
    },
    {
      "period": "2011-Q1",
      "value": 101.88670814949336
    },
    {
      "period": "2011-Q2",
      "value": 103.11012579054339
    },
    {
      "period": "2011-Q3",
      "value": 102.69286098002976
    },
    {
      "period": "2011-Q4",
      "value": 102.1013475606432
    },
    {
      "period": "2012-Q1",
      "value": 101.26319096562945
    },
    {
      "period": "2012-Q2",
      "value": 100.45711758699676
    },
    {
      "period": "2012-Q3",
      "value": 103.83754830336366
    },
    {
      "period": "2012-Q4",
      "value": 101.05358848892871
    },
    {
      "period": "2013-Q1",
      "value": 101.5099912574178
    },
    {
      "period": "2013-Q2",
      "value": 102.4587741535633
    },
    {
      "period": "2013-Q3",
      "value": 103.04964428195127
    },
    {
      "period": "2013-Q4",
      "value": 100.84641411382371
    },
    {
      "period": "2014-Q1",
      "value": 100.93967151215563
    },
    {
      "period": "2014-Q2",
      "value": 102.50931305793122
    },
    {
      "period": "2014-Q3",
      "value": 103.13721288694488
    },
    {
      "period": "2014-Q4",
      "value": 102.51721000008767
    },
    {
      "period": "2015-Q1",
      "value": 103.70301876575284
    },
    {
      "period": "2015-Q2",
      "value": 104.66202676305204
    },
    {
      "period": "2015-Q3",
      "value": 106.16289205733067
    },
    {
      "period": "2015-Q4",
      "value": 104.4394247875762
    },
    {
      "period": "2016-Q1",
      "value": 102.91956337778592
    },
    {
      "period": "2016-Q2",
      "value": 103.46036949846777
    },
    {
      "period": "2016-Q3",
      "value": 104.38753890405306
    },
    {
      "period": "2016-Q4",
      "value": 104.46423803262962
    },
    {
      "period": "2017-Q1",
      "value": 103.35103801871068
    },
    {
      "period": "2017-Q2",
      "value": 103.7471977309234
    },
    {
      "period": "2017-Q3",
      "value": 105.91018661595211
    },
    {
      "period": "2017-Q4",
      "value": 103.00359620108993
    },
    {
      "period": "2018-Q1",
      "value": 103.78439377181462
    },
    {
      "period": "2018-Q2",
      "value": 103.42178401695907
    },
    {
      "period": "2018-Q3",
      "value": 102.6636913987079
    },
    {
      "period": "2018-Q4",
      "value": 101.04512230283213
    },
    {
      "period": "2019-Q1",
      "value": 101.52054281018816
    },
    {
      "period": "2019-Q2",
      "value": 101.89825623857698
    },
    {
      "period": "2019-Q3",
      "value": 103.48985696208653
    },
    {
      "period": "2019-Q4",
      "value": 103.45945107634235
    },
    {
      "period": "2020-Q1",
      "value": 103.29070057516533
    },
    {
      "period": "2020-Q2",
      "value": 104.24106412921742
    },
    {
      "period": "2020-Q3",
      "value": 102.70763543261563
    },
    {
      "period": "2020-Q4",
      "value": 104.1464956361052
    },
    {
      "period": "2021-Q1",
      "value": 104.18687976186138
    },
    {
      "period": "2021-Q2",
      "value": 102.60491569391122
    },
    {
      "period": "2021-Q3",
      "value": 102.99054602945401
    },
    {
      "period": "2021-Q4",
      "value": 102.475967057363
    },
    {
      "period": "2022-Q1",
      "value": 101.54439561132206
    },
    {
      "period": "2022-Q2",
      "value": 102.44785279637512
    },
    {
      "period": "2022-Q3",
      "value": 102.78620172094215
    },
    {
      "period": "2022-Q4",
      "value": 103.80111263745471
    },
    {
      "period": "2023-Q1",
      "value": 105.96940623905576
    },
    {
      "period": "2023-Q2",
      "value": 106.77248461461429
    },
    {
      "period": "2023-Q3",
      "value": 107.3654430843665
    },
    {
      "period": "2023-Q4",
      "value": 107.31249603300131
    },
    {
      "period": "2024-Q1",
      "value": 107.51249242832964
    },
    {
      "period": "2024-Q2",
      "value": 108.20525855237908
    },
    {
      "period": "2024-Q3",
      "value": 108.29223948039593
    },
    {
      "period": "2024-Q4",
      "value": 110.78761238023725
    },
    {
      "period": "2025-Q1",
      "value": 109.9231428442915
    },
    {
      "period": "2025-Q2",
      "value": 109.83540827418048
    },
    {
      "period": "2025-Q3",
      "value": 111.46478168732007
    },
    {
      "period": "2025-Q4",
      "value": 110.32866696762949
    },
    {
      "period": "2026-Q1",
      "value": 110.5513246446678
    },
    {
      "period": "2026-Q2",
      "value": 112.03681987481187
    }
  ]
}