{
  "id": "us-ia_manufactura_total_nay_bls",
  "meta": {
    "id": "us-ia_manufactura_total_nay_bls",
    "nombre": "Empleo manufacturero - Total manufacturing (national reference) (Iowa)",
    "pais": "US",
    "region_code": "19",
    "sector_id": "manufactura_total",
    "fuente": "BLS - State and Area Employment (mock)",
    "periodicidad": "mensual",
    "unidad": "Miles de empleos (sintético)",
    "proxy_type": "labor_input",
    "ultima_actualizacion": "2026-06-30",
    "proxima_actualizacion_estimada": "2026-07-30"
  },
  "observations": [
    {
      "period": "2010-01",
      "value": 100.426878629213
    },
    {
      "period": "2010-02",
      "value": 100.80120624217238
    },
    {
      "period": "2010-03",
      "value": 100.24866125562541
    },
    {
      "period": "2010-04",
      "value": 99.69491698848691
    },
    {
      "period": "2010-05",
      "value": 99.57068266534199
    },
    {
      "period": "2010-06",
      "value": 99.57932074733274
    },
    {
      "period": "2010-07",
      "value": 100.82347287125712
    },
    {
      "period": "2010-08",
      "value": 101.83598121631243
    },
    {
      "period": "2010-09",
      "value": 100.64278114390972
    },
    {
      "period": "2010-10",
      "value": 100.84595026299829
    },
    {
      "period": "2010-11",
      "value": 102.204898929416
    },
    {
      "period": "2010-12",
      "value": 101.99865151555217
    },
    {
      "period": "2011-01",
      "value": 101.93739003688906
    },
    {
      "period": "2011-02",
      "value": 102.83521373039918
    },
    {
      "period": "2011-03",
      "value": 101.51564755302392
    },
    {
      "period": "2011-04",
      "value": 101.91945137970285
    },
    {
      "period": "2011-05",
      "value": 101.51386729781927
    },
    {
      "period": "2011-06",
      "value": 102.49367161124798
    },
    {
      "period": "2011-07",
      "value": 101.32966370382262
    },
    {
      "period": "2011-08",
      "value": 101.66945460356837
    },
    {
      "period": "2011-09",
      "value": 102.30544801829396
    },
    {
      "period": "2011-10",
      "value": 104.92882753498398
    },
    {
      "period": "2011-11",
      "value": 103.83544866749318
    },
    {
      "period": "2011-12",
      "value": 104.7430998663234
    },
    {
      "period": "2012-01",
      "value": 104.23369196981412
    },
    {
      "period": "2012-02",
      "value": 104.83451048033862
    },
    {
      "period": "2012-03",
      "value": 105.26047493235957
    },
    {
      "period": "2012-04",
      "value": 105.92730162962032
    },
    {
      "period": "2012-05",
      "value": 105.34403538705602
    },
    {
      "period": "2012-06",
      "value": 104.86458223538216
    },
    {
      "period": "2012-07",
      "value": 104.8155347060953
    },
    {
      "period": "2012-08",
      "value": 104.61874558101506
    },
    {
      "period": "2012-09",
      "value": 105.57828576846072
    },
    {
      "period": "2012-10",
      "value": 104.60395600729365
    },
    {
      "period": "2012-11",
      "value": 104.65866013321443
    },
    {
      "period": "2012-12",
      "value": 105.6799630769299
    },
    {
      "period": "2013-01",
      "value": 103.39430230713974
    },
    {
      "period": "2013-02",
      "value": 102.70868238747839
    },
    {
      "period": "2013-03",
      "value": 103.0578589590498
    },
    {
      "period": "2013-04",
      "value": 102.66918171313857
    },
    {
      "period": "2013-05",
      "value": 101.53437783854987
    },
    {
      "period": "2013-06",
      "value": 102.9073647565479
    },
    {
      "period": "2013-07",
      "value": 101.2985546466507
    },
    {
      "period": "2013-08",
      "value": 103.35827142864173
    },
    {
      "period": "2013-09",
      "value": 102.1353838697439
    },
    {
      "period": "2013-10",
      "value": 106.51424704354721
    },
    {
      "period": "2013-11",
      "value": 104.43416469004691
    },
    {
      "period": "2013-12",
      "value": 104.95156642316311
    },
    {
      "period": "2014-01",
      "value": 104.65879094072135
    },
    {
      "period": "2014-02",
      "value": 105.04774126948192
    },
    {
      "period": "2014-03",
      "value": 103.98921526232776
    },
    {
      "period": "2014-04",
      "value": 106.30619979334283
    },
    {
      "period": "2014-05",
      "value": 105.96137507286956
    },
    {
      "period": "2014-06",
      "value": 106.24728088912215
    },
    {
      "period": "2014-07",
      "value": 105.09641013024469
    },
    {
      "period": "2014-08",
      "value": 105.18224124037852
    },
    {
      "period": "2014-09",
      "value": 105.16855881840783
    },
    {
      "period": "2014-10",
      "value": 105.93398954478995
    },
    {
      "period": "2014-11",
      "value": 106.64363520557889
    },
    {
      "period": "2014-12",
      "value": 106.48979959174787
    },
    {
      "period": "2015-01",
      "value": 104.38011260011818
    },
    {
      "period": "2015-02",
      "value": 104.5438554200301
    },
    {
      "period": "2015-03",
      "value": 105.21629315327554
    },
    {
      "period": "2015-04",
      "value": 105.93779312911398
    },
    {
      "period": "2015-05",
      "value": 106.36699819389901
    },
    {
      "period": "2015-06",
      "value": 105.51900454530094
    },
    {
      "period": "2015-07",
      "value": 107.59414400795056
    },
    {
      "period": "2015-08",
      "value": 108.01846769121646
    },
    {
      "period": "2015-09",
      "value": 107.62373542630826
    },
    {
      "period": "2015-10",
      "value": 106.25751650945503
    },
    {
      "period": "2015-11",
      "value": 107.67839232269617
    },
    {
      "period": "2015-12",
      "value": 107.7732329779182
    },
    {
      "period": "2016-01",
      "value": 105.52635866660567
    },
    {
      "period": "2016-02",
      "value": 105.62420270667671
    },
    {
      "period": "2016-03",
      "value": 105.36239881865708
    },
    {
      "period": "2016-04",
      "value": 104.81968019294952
    },
    {
      "period": "2016-05",
      "value": 103.60375126596108
    },
    {
      "period": "2016-06",
      "value": 103.78865753988592
    },
    {
      "period": "2016-07",
      "value": 103.92158626748764
    },
    {
      "period": "2016-08",
      "value": 105.39773848372297
    },
    {
      "period": "2016-09",
      "value": 105.75558913300041
    },
    {
      "period": "2016-10",
      "value": 105.09458789466115
    },
    {
      "period": "2016-11",
      "value": 105.08200210487584
    },
    {
      "period": "2016-12",
      "value": 106.37766658566636
    },
    {
      "period": "2017-01",
      "value": 108.1149618306819
    },
    {
      "period": "2017-02",
      "value": 106.74671723024937
    },
    {
      "period": "2017-03",
      "value": 107.25563615796347
    },
    {
      "period": "2017-04",
      "value": 107.26762980617326
    },
    {
      "period": "2017-05",
      "value": 108.07931946476114
    },
    {
      "period": "2017-06",
      "value": 108.67497754996224
    },
    {
      "period": "2017-07",
      "value": 108.09945168178544
    },
    {
      "period": "2017-08",
      "value": 107.78829812105812
    },
    {
      "period": "2017-09",
      "value": 107.57053841520752
    },
    {
      "period": "2017-10",
      "value": 108.13476503510404
    },
    {
      "period": "2017-11",
      "value": 107.68152655493319
    },
    {
      "period": "2017-12",
      "value": 108.7877030913731
    },
    {
      "period": "2018-01",
      "value": 109.76906729492184
    },
    {
      "period": "2018-02",
      "value": 109.14882371842324
    },
    {
      "period": "2018-03",
      "value": 110.92251367555929
    },
    {
      "period": "2018-04",
      "value": 110.01765400457174
    },
    {
      "period": "2018-05",
      "value": 108.88986209463089
    },
    {
      "period": "2018-06",
      "value": 111.25214232415256
    },
    {
      "period": "2018-07",
      "value": 106.5432092411139
    },
    {
      "period": "2018-08",
      "value": 107.4846766541372
    },
    {
      "period": "2018-09",
      "value": 108.16295653493957
    },
    {
      "period": "2018-10",
      "value": 104.2638288441059
    },
    {
      "period": "2018-11",
      "value": 104.19503491111448
    },
    {
      "period": "2018-12",
      "value": 104.81546428995202
    },
    {
      "period": "2019-01",
      "value": 105.29594988027725
    },
    {
      "period": "2019-02",
      "value": 104.4893466934523
    },
    {
      "period": "2019-03",
      "value": 105.62712110266816
    },
    {
      "period": "2019-04",
      "value": 107.30996354137652
    },
    {
      "period": "2019-05",
      "value": 107.12358421425755
    },
    {
      "period": "2019-06",
      "value": 107.05622630652157
    },
    {
      "period": "2019-07",
      "value": 106.85404519141927
    },
    {
      "period": "2019-08",
      "value": 107.54767029094835
    },
    {
      "period": "2019-09",
      "value": 106.60442042444842
    },
    {
      "period": "2019-10",
      "value": 108.96442299039154
    },
    {
      "period": "2019-11",
      "value": 107.83166112689635
    },
    {
      "period": "2019-12",
      "value": 107.87981819792384
    },
    {
      "period": "2020-01",
      "value": 108.16775682138237
    },
    {
      "period": "2020-02",
      "value": 108.53086731825684
    },
    {
      "period": "2020-03",
      "value": 108.36205020483942
    },
    {
      "period": "2020-04",
      "value": 110.38212716583222
    },
    {
      "period": "2020-05",
      "value": 109.91101689813671
    },
    {
      "period": "2020-06",
      "value": 109.28981528031738
    },
    {
      "period": "2020-07",
      "value": 111.99526924861125
    },
    {
      "period": "2020-08",
      "value": 112.11188588085042
    },
    {
      "period": "2020-09",
      "value": 111.50491047033391
    },
    {
      "period": "2020-10",
      "value": 110.6297348960031
    },
    {
      "period": "2020-11",
      "value": 110.60099503623339
    },
    {
      "period": "2020-12",
      "value": 113.05632960560179
    },
    {
      "period": "2021-01",
      "value": 112.80427605882274
    },
    {
      "period": "2021-02",
      "value": 112.74298568186092
    },
    {
      "period": "2021-03",
      "value": 113.3076544775102
    },
    {
      "period": "2021-04",
      "value": 110.51469815143477
    },
    {
      "period": "2021-05",
      "value": 111.97500308656105
    },
    {
      "period": "2021-06",
      "value": 111.1790254272916
    },
    {
      "period": "2021-07",
      "value": 111.03990432945488
    },
    {
      "period": "2021-08",
      "value": 111.08003059432181
    },
    {
      "period": "2021-09",
      "value": 110.87608844931192
    },
    {
      "period": "2021-10",
      "value": 109.35735951727028
    },
    {
      "period": "2021-11",
      "value": 109.52032344694706
    },
    {
      "period": "2021-12",
      "value": 109.97039169907222
    },
    {
      "period": "2022-01",
      "value": 110.52879546042604
    },
    {
      "period": "2022-02",
      "value": 110.53548016378103
    },
    {
      "period": "2022-03",
      "value": 109.722942690461
    },
    {
      "period": "2022-04",
      "value": 108.52920803102806
    },
    {
      "period": "2022-05",
      "value": 108.20772862949724
    },
    {
      "period": "2022-06",
      "value": 108.57215900976763
    },
    {
      "period": "2022-07",
      "value": 108.08745894148386
    },
    {
      "period": "2022-08",
      "value": 107.04960779009407
    },
    {
      "period": "2022-09",
      "value": 107.14682608650699
    },
    {
      "period": "2022-10",
      "value": 107.78973254029862
    },
    {
      "period": "2022-11",
      "value": 108.11949774122817
    },
    {
      "period": "2022-12",
      "value": 108.27704005102338
    },
    {
      "period": "2023-01",
      "value": 109.05077773589397
    },
    {
      "period": "2023-02",
      "value": 108.98948979930302
    },
    {
      "period": "2023-03",
      "value": 108.97248700257626
    },
    {
      "period": "2023-04",
      "value": 110.2616553054146
    },
    {
      "period": "2023-05",
      "value": 109.69484158784061
    },
    {
      "period": "2023-06",
      "value": 107.6452367065202
    },
    {
      "period": "2023-07",
      "value": 109.57645789287848
    },
    {
      "period": "2023-08",
      "value": 109.61947738343426
    },
    {
      "period": "2023-09",
      "value": 109.68207054403749
    },
    {
      "period": "2023-10",
      "value": 108.89292658625726
    },
    {
      "period": "2023-11",
      "value": 108.3970915261715
    },
    {
      "period": "2023-12",
      "value": 108.04413013929887
    },
    {
      "period": "2024-01",
      "value": 106.34510638737598
    },
    {
      "period": "2024-02",
      "value": 107.86391286727584
    },
    {
      "period": "2024-03",
      "value": 105.79721281314268
    },
    {
      "period": "2024-04",
      "value": 108.34425843152302
    },
    {
      "period": "2024-05",
      "value": 106.81705807328916
    },
    {
      "period": "2024-06",
      "value": 107.69343742339004
    },
    {
      "period": "2024-07",
      "value": 108.5745364303484
    },
    {
      "period": "2024-08",
      "value": 108.8179082290227
    },
    {
      "period": "2024-09",
      "value": 108.99381735341835
    },
    {
      "period": "2024-10",
      "value": 111.00155273169155
    },
    {
      "period": "2024-11",
      "value": 110.83974890955552
    },
    {
      "period": "2024-12",
      "value": 109.9512264549064
    },
    {
      "period": "2025-01",
      "value": 108.67530379427029
    },
    {
      "period": "2025-02",
      "value": 108.9450897498682
    },
    {
      "period": "2025-03",
      "value": 110.0890221557895
    },
    {
      "period": "2025-04",
      "value": 109.35361125166577
    },
    {
      "period": "2025-05",
      "value": 108.63571451834298
    },
    {
      "period": "2025-06",
      "value": 108.90610941645976
    },
    {
      "period": "2025-07",
      "value": 109.55313361431065
    },
    {
      "period": "2025-08",
      "value": 110.02101709633187
    },
    {
      "period": "2025-09",
      "value": 110.72346542696023
    },
    {
      "period": "2025-10",
      "value": 111.23805119153101
    },
    {
      "period": "2025-11",
      "value": 112.37481305229578
    },
    {
      "period": "2025-12",
      "value": 110.16830856019233
    },
    {
      "period": "2026-01",
      "value": 111.33154389205836
    },
    {
      "period": "2026-02",
      "value": 111.10136614672791
    },
    {
      "period": "2026-03",
      "value": 111.65858224222494
    },
    {
      "period": "2026-04",
      "value": 111.56600854750143
    },
    {
      "period": "2026-05",
      "value": 111.71728863317522
    },
    {
      "period": "2026-06",
      "value": 110.66071315466255
    }
  ]
}